Workbook

Sheet questoes
A1: ID | B1: DISCIPLINA | C1: TEMA | D1: TOPICO | E1: NIVEL | F1: ENUNCIADO | G1: A | H1: B | I1: C | J1: D | K1: E | L1: CORRETO | M1: CORRETO FORM | N1: GABARITO | O1: FEEDBACK | P1: FONTE | Q1: PAGINA
A2: ECO_T1_001 | B2: Economia | C2: Tema 1 | D2: Introdução à Economia | E2: Ouro | F2: Uma cooperativa agrícola busca melhorar a utilização de máquinas, trabalhadores e matéria-prima para aumentar a eficiência produtiva. Segundo a Economia, qual é o objetivo principal dessa ciência? | G2: Eliminar totalmente a escassez. | H2: Controlar apenas o comércio internacional. | I2: Melhorar a alocação dos recursos para produção de bens e serviços. | J2: Produzir somente bens industriais. | K2: Aumentar o consumo sem planejamento. | L2: C | M2: =_xlfn.XLOOKUP(questoes!$L2,Tabela2[LETRA],Tabela2[IND],"",0) -> 2 | N2: 2 | O2: A Economia é uma ciência social que analisa os sistemas de produção de bens e serviços com o objetivo de proporcionar a melhor alocação dos recursos produtivos disponíveis para atender às necessidades da sociedade. Isso significa utilizar máquinas, trabalhadores, terra, capital e matéria-prima da forma mais eficiente possível. Na prática, uma cooperativa agrícola precisa decidir como utilizar tratores, mão de obra, sementes e fertilizantes sem desperdícios, buscando maior produtividade e melhor resultado econômico. | P2: Tema 1: Princípios de Economia, Tópico 1: Introdução à Economia, Item1: Conceitos básicos, Pág. 10. | Q2: 10
A3: ECO_T1_002 | B3: Economia | C3: Tema 1 | D3: Introdução à Economia | E3: Fácil | F3: O termo “economia” possui origem grega e pode ser traduzido como: | G3: Administração do lar. | H3: Controle da moeda. | I3: Planejamento tributário. | J3: Organização industrial. | K3: Administração pública. | L3: A | M3: =_xlfn.XLOOKUP(questoes!$L3,Tabela2[LETRA],Tabela2[IND],"",0) -> 0 | N3: 0 | O3: O termo “economia” deriva das palavras gregas “oikos” (casa) e “nomos” (costume ou lei), podendo ser traduzido como “administração do lar”. A apostila destaca que a Economia estuda a atividade produtiva e a forma como os recursos são organizados para satisfazer as necessidades humanas. Esse conceito ajuda a compreender que tanto uma família quanto uma empresa precisam administrar recursos limitados para atender suas necessidades. | P3: Tema 1: Princípios de Economia, Tópico 1: Introdução à Economia, Item1: Conceitos básicos, Pág. 10. | Q3: 10
A4: ECO_T1_003 | B4: Economia | C4: Tema 1 | D4: Introdução à Economia | E4: Médio | F4: O principal problema estudado pela Economia está relacionado: | G4: Ao excesso de produtos. | H4: À escassez dos recursos produtivos. | I4: À ausência de consumidores. | J4: À falta de tecnologia. | K4: Ao crescimento industrial. | L4: B | M4: =_xlfn.XLOOKUP(questoes!$L4,Tabela2[LETRA],Tabela2[IND],"",0) -> 1 | N4: 1 | O4: Segundo a apostila, o principal problema estudado pela Economia é a escassez dos recursos produtivos. Enquanto as necessidades humanas são ilimitadas e se renovam constantemente, os recursos disponíveis para produzir bens e serviços são limitados. Isso pode ser observado quando famílias desejam melhorar sua qualidade de vida adquirindo novos bens, como casa, carro, roupas e serviços, mas possuem renda limitada. | P4: Tema 1: Princípios de Economia, Tópico 1: Introdução à Economia, Item1: Conceitos básicos, Pág. 10. | Q4: 10
A5: ECO_T1_004 | B5: Economia | C5: Tema 1 | D5: Introdução à Economia | E5: Fácil | F5: Qual alternativa apresenta exemplos de necessidades humanas citadas na apostila? | G5: Máquinas, tratores e fertilizantes. | H5: Alimentação, moradia e lazer. | I5: PIB, inflação e exportação. | J5: Crédito, juros e impostos. | K5: Comércio exterior e câmbio. | L5: B | M5: =_xlfn.XLOOKUP(questoes!$L5,Tabela2[LETRA],Tabela2[IND],"",0) -> 1 | N5: 1 | O5: A apostila apresenta como exemplos de necessidades humanas a alimentação, educação, moradia, vestuário, transporte, comunicação, lazer e artigos de luxo. Essas necessidades podem ser individuais ou coletivas e são satisfeitas por meio do consumo de bens e serviços. No cotidiano, uma pessoa necessita de alimentação e moradia, mas também busca lazer, comunicação e conforto. | P5: Tema 1: Princípios de Economia, Tópico 1: Introdução à Economia. Pág. 10. | Q5: 10
A6: ECO_T1_005 | B6: Economia | C6: Tema 1 | D6: Introdução à Economia | E6: Médio | F6: Quando uma empresa define quais produtos serão fabricados e em quais quantidades, ela está respondendo à pergunta econômica: | G6: Como produzir? | H6: Para quem produzir? | I6: O que produzir? | J6: Quando produzir? | K6: Quanto exportar? | L6: C | M6: =_xlfn.XLOOKUP(questoes!$L6,Tabela2[LETRA],Tabela2[IND],"",0) -> 2 | N6: 2 | O6: A questão “o que produzir?” está relacionada à escolha dos bens e serviços que serão disponibilizados aos consumidores. | P6: Tema 1: Princípios de Economia, Tópico 1: Introdução à Economia, Item1: Conceitos básicos, Pág. 11. | Q6: 11
A7: ECO_T1_006 | B7: Economia | C7: Tema 1 | D7: Introdução à Economia | E7: Fácil | F7: A escolha da tecnologia utilizada por uma indústria para fabricar seus produtos está relacionada à questão econômica: | G7: Para quem produzir? | H7: Como produzir? | I7: Quanto vender? | J7: Quem consumir? | K7: O que importar? | L7: B | M7: =_xlfn.XLOOKUP(questoes!$L7,Tabela2[LETRA],Tabela2[IND],"",0) -> 1 | N7: 1 | O7: A pergunta “como produzir?” refere-se ao método ou tecnologia utilizada na produção de bens e serviços. | P7: Princípios de Economia, Tópico 1: Introdução à Economia, Item1: Conceitos básicos, Pág. 11. | Q7: 11
A8: ECO_T1_007 | B8: Economia | C8: Tema 1 | D8: Introdução à Economia | E8: Médio | F8: A definição do público consumidor de determinado produto está relacionada à questão econômica: | G8: Como produzir? | H8: Quanto investir? | I8: Quando produzir? | J8: Para quem produzir? | K8: O que exportar? | L8: D | M8: =_xlfn.XLOOKUP(questoes!$L8,Tabela2[LETRA],Tabela2[IND],"",0) -> 3 | N8: 3 | O8: A questão “para quem produzir?” relaciona-se com a definição de quem consumirá os bens e serviços produzidos. | P8: Tema 1: Princípios de Economia, Tópico 1: Introdução à Economia, Item1: Conceitos básicos, Pág. 11. | Q8: 11
A9: ECO_T1_008 | B9: Economia | C9: Tema 1 | D9: Introdução à Economia | E9: Ouro | F9: O estudo do comportamento dos consumidores e empresas em diferentes situações de mercado pertence à: | G9: Macroeconomia. | H9: Economia internacional. | I9: Microeconomia. | J9: Economia financeira. | K9: Economia ambiental. | L9: C | M9: =_xlfn.XLOOKUP(questoes!$L9,Tabela2[LETRA],Tabela2[IND],"",0) -> 2 | N9: 2 | O9: A Microeconomia analisa o comportamento das famílias e empresas nas situações de mercado. No sistema econômico, as famílias participam tanto consumindo produtos quanto oferecendo mão de obra às empresas. | P9: Tema 1: Princípios de Economia, Tópico 1: Introdução à Economia, Item1: Conceitos básicos, Pág. 11. | Q9: 11
A10: ECO_T1_009 | B10: Economia | C10: Tema 1 | D10: Introdução à Economia | E10: Médio | F10: O Produto Interno Bruto (PIB), o nível de emprego e o sistema monetário são estudados principalmente pela: | G10: Microeconomia. | H10: Macroeconomia. | I10: Administração financeira. | J10: Economia rural. | K10: Contabilidade. | L10: B | M10: =_xlfn.XLOOKUP(questoes!$L10,Tabela2[LETRA],Tabela2[IND],"",0) -> 1 | N10: 1 | O10: A Macroeconomia estuda agregados econômicos como PIB, emprego e sistema monetário. | P10: Tema 1: Princípios de Economia, Tópico 1: Introdução à Economia, Item1: Conceitos básicos, Pág. 11. | Q10: 11
A11: ECO_T1_010 | B11: Economia | C11: Tema 1 | D11: Classificação de bens e serviços | E11: Fácil | F11: Bens econômicos são aqueles que: | G11: Possuem oferta ilimitada. | H11: Não exigem trabalho humano. | I11: São escassos e possuem valor de mercado. | J11: Existem apenas no setor industrial. | K11: Não atendem necessidades humanas. | L11: C | M11: =_xlfn.XLOOKUP(questoes!$L11,Tabela2[LETRA],Tabela2[IND],"",0) -> 2 | N11: 2 | O11: Os bens econômicos são relativamente escassos e necessitam de trabalho humano para serem obtidos. | P11: Tema 1: Princípios de Economia, Tópico 1: Introdução à Economia, Item 2: Classificação de bens e serviços. Pág. 11. | Q11: 11
A12: ECO_T1_011 | B12: Economia | C12: Tema 1 | D12: Classificação de bens e serviços | E12: Fácil | F12: Qual alternativa apresenta um exemplo de bem NÃO econômico? | G12: Combustível. | H12: Geladeira. | I12: Ar atmosférico. | J12: Automóvel. | K12: Produto de limpeza. | L12: C | M12: =_xlfn.XLOOKUP(questoes!$L12,Tabela2[LETRA],Tabela2[IND],"",0) -> 2 | N12: 2 | O12: O ar não é considerado um bem econômico porque possui oferta ilimitada e não requer trabalho humano para utilização. . | P12: Tema 1: Princípios de Economia, Tópico 1: Introdução à Economia, Item 2: Classificação de bens e serviços. Pág. 12. | Q12: 12
A13: ECO_T1_012 | B13: Economia | C13: Tema 1 | D13: Classificação de bens e serviços | E13: Fácil | F13: Produtos de limpeza e combustíveis são exemplos de: | G13: Bens de capital. | H13: Bens intermediários. | I13: Bens de consumo não duráveis. | J13: Bens imateriais. | K13: Bens finais duráveis. | L13: C | M13: =_xlfn.XLOOKUP(questoes!$L13,Tabela2[LETRA],Tabela2[IND],"",0) -> 2 | N13: 2 | O13: Bens de consumo não duráveis são utilizados rapidamente, como alimentos, combustíveis e produtos de limpeza. | P13: Tema 1: Princípios de Economia, Tópico 2: Classificação de bens e serviços. Pág. 12. | Q13: 12
A14: ECO_T1_013 | B14: Economia | C14: Tema 1 | D14: Classificação de bens e serviços | E14: Fácil | F14: Automóveis e geladeiras são classificados como: | G14: Bens intermediários. | H14: Bens imateriais. | I14: Bens de capital. | J14: Bens de consumo duráveis. | K14: Bens perecíveis. | L14: D | M14: =_xlfn.XLOOKUP(questoes!$L14,Tabela2[LETRA],Tabela2[IND],"",0) -> 3 | N14: 3 | O14: Bens duráveis podem ser utilizados por um longo período de tempo. | P14: Tema 1: Princípios de Economia, Tópico 2: Classificação de bens e serviços. Pág. 12. | Q14: 12
A15: ECO_T1_014 | B15: Economia | C15: Tema 1 | D15: Classificação de bens e serviços | E15: Médio | F15: Em uma propriedade rural, tratores e implementos agrícolas utilizados na produção são classificados como: | G15: Bens finais. | H15: Bens de capital. | I15: Bens imateriais. | J15: Bens de consumo. | K15: Bens perecíveis. | L15: B | M15: =_xlfn.XLOOKUP(questoes!$L15,Tabela2[LETRA],Tabela2[IND],"",0) -> 1 | N15: 1 | O15: Bens de capital compõem o sistema produtivo e são utilizados para produzir outros bens. | Q15: 11-13
A16: ECO_T1_015 | B16: Economia | C16: Tema 1 | D16: Classificação de bens e serviços | E16: Médio | F16: Os fertilizantes utilizados pelo agricultor para a produção de soja representam: | G16: Bens finais. | H16: Bens imateriais. | I16: Bens intermediários. | J16: Bens duráveis. | K16: Bens de luxo. | L16: C | M16: =_xlfn.XLOOKUP(questoes!$L16,Tabela2[LETRA],Tabela2[IND],"",0) -> 2 | N16: 2 | O16: Bens intermediários são utilizados na produção de outros bens. | P16: Tema 1: Princípios de Economia, Tópico 2: Classificação de bens e serviços. Pág. 11-13. | Q16: 11-13
A17: ECO_T1_016 | B17: Economia | C17: Tema 1 | D17: Classificação de bens e serviços | E17: Fácil | F17: O serviço prestado por um técnico agrícola é considerado um: | G17: Bem de capital. | H17: Bem final. | I17: Bem imaterial. | J17: Bem intermediário. | K17: Bem durável. | L17: C | M17: =_xlfn.XLOOKUP(questoes!$L17,Tabela2[LETRA],Tabela2[IND],"",0) -> 2 | N17: 2 | O17: Os bens imateriais não possuem existência física, como serviços de assistência técnica e educação. | P17: Tema 1: Princípios de Economia, Tópico 2: Classificação de bens e serviços. Pág. 11-13. | Q17: 11-13
A18: ECO_T1_017 | B18: Economia | C18: Tema 1 | D18: Fatores de produção | E18: Médio | F18: Os fatores de produção essenciais utilizados pelas empresas são: | G18: Mercado, moeda e impostos. | H18: Capital, terra e trabalho. | I18: Famílias, empresas e governo. | J18: Máquinas, sementes e fertilizantes. | K18: Oferta, demanda e preço. | L18: B | M18: =_xlfn.XLOOKUP(questoes!$L18,Tabela2[LETRA],Tabela2[IND],"",0) -> 1 | N18: 1 | O18: Os fatores de produção fundamentais são capital, terra e trabalho. | P18: Tema 1: Princípios de Economia, Tópico 3: Fatores de produção. Pág. 13-14. | Q18: 13-14
A19: ECO_T1_018 | B19: Economia | C19: Tema 1 | D19: Fatores de produção | E19: Difícil | F19: Um produtor utiliza um trator para preparar o solo para o plantio de feijão. Nesse caso, o trator representa qual fator de produção? | G19: Trabalho. | H19: Terra. | I19: Capital. | J19: Moeda. | K19: Consumo. | L19: C | M19: =_xlfn.XLOOKUP(questoes!$L19,Tabela2[LETRA],Tabela2[IND],"",0) -> 2 | N19: 2 | O19: Máquinas e equipamentos utilizados no sistema produtivo são classificados como capital. | P19: Tema 1: Princípios de Economia, Tópico 3: Fatores de produção. Pág. 13-14. | Q19: 13-14
A20: ECO_T1_019 | B20: Economia | C20: Tema 1 | D20: Fatores de produção | E20: Fácil | F20: Florestas, recursos minerais e recursos hídricos fazem parte do fator de produção: | G20: Capital. | H20: Terra. | I20: Trabalho. | J20: Tecnologia. | K20: Consumo. | L20: B | M20: =_xlfn.XLOOKUP(questoes!$L20,Tabela2[LETRA],Tabela2[IND],"",0) -> 1 | N20: 1 | O20: O fator terra inclui todos os recursos naturais utilizados nos sistemas produtivos. | P20: Tema 1: Princípios de Economia, Tópico 3: Fatores de produção. Pág. 13-14. | Q20: 13-14
A21: ECO_T1_020 | B21: Economia | C21: Tema 1 | D21: Fatores de produção | E21: Médio | F21: O esforço físico e mental necessário para realizar atividades produtivas corresponde ao fator de produção: | G21: Capital. | H21: Terra. | I21: Mercado. | J21: Trabalho. | K21: Moeda. | L21: D | M21: =_xlfn.XLOOKUP(questoes!$L21,Tabela2[LETRA],Tabela2[IND],"",0) -> 3 | N21: 3 | O21: O fator trabalho consiste na capacidade produtiva das pessoas envolvidas nos sistemas produtivos. | P21: Tema 1: Princípios de Economia, Tópico 3: Fatores de produção. Pág. 13-14. | Q21: 13-14
A22: ECO_T1_021 | B22: Economia | C22: Tema 1 | D22: Agentes econômicos | E22: Fácil | F22: Quais são os agentes econômicos de uma sociedade? | G22: Empresas, bancos e consumidores. | H22: Famílias, empresas e governo. | I22: Mercado, moeda e empresas. | J22: Capital, trabalho e terra. | K22: Indústria, comércio e serviços. | L22: B | M22: =_xlfn.XLOOKUP(questoes!$L22,Tabela2[LETRA],Tabela2[IND],"",0) -> 1 | N22: 1 | O22: Os principais agentes econômicos são famílias, empresas e governo. No sistema econômico, as famílias participam tanto consumindo produtos quanto oferecendo mão de obra às empresas. | P22: Tema 1: Princípios de Economia, Tópico 4: Agentes econômicos. Pág. 14-15. | Q22: 14-15
A23: ECO_T1_022 | B23: Economia | C23: Tema 1 | D23: Agentes econômicos | E23: Médio | F23: Além de consumir bens e serviços, as famílias também têm a função de: | G23: Produzir moeda. | H23: Oferecer recursos produtivos às empresas. | I23: Fiscalizar a economia. | J23: Definir políticas públicas. | K23: Controlar exportações. | L23: B | M23: =_xlfn.XLOOKUP(questoes!$L23,Tabela2[LETRA],Tabela2[IND],"",0) -> 1 | N23: 1 | O23: As famílias oferecem recursos produtivos, especialmente mão de obra, às empresas. No sistema econômico, as famílias participam tanto consumindo produtos quanto oferecendo mão de obra às empresas. | P23: ]Tema 1: Princípios de Economia, Tópico 4: Agentes econômicos. Pág. 14-15. | Q23: 14-15
A24: ECO_T1_023 | B24: Economia | C24: Tema 1 | D24: Agentes econômicos | E24: Médio | F24: A principal função das empresas em um sistema econômico é: | G24: Controlar a inflação. | H24: Produzir e comercializar bens e serviços. | I24: Emitir moeda. | J24: Fiscalizar o mercado. | K24: Regular importações. | L24: B | M24: =_xlfn.XLOOKUP(questoes!$L24,Tabela2[LETRA],Tabela2[IND],"",0) -> 1 | N24: 1 | O24: As empresas produzem e comercializam bens e serviços utilizando fatores de produção. | P24: Tema 1: Princípios de Economia, Tópico 4: Agentes econômicos. Pág. 14-15. | Q24: 14-15
A25: ECO_T1_024 | B25: Economia | C25: Tema 1 | D25: Agentes econômicos | E25: Difícil | F25: As ações do governo relacionadas à fiscalização da economia e provisão de moeda recebem o nome de: | G25: Estratégias privadas. | H25: Políticas públicas. | I25: Atividades comerciais. | J25: Administração empresarial. | K25: Políticas industriais. | L25: B | M25: =_xlfn.XLOOKUP(questoes!$L25,Tabela2[LETRA],Tabela2[IND],"",0) -> 1 | N25: 1 | O25: As ações do governo voltadas ao funcionamento do sistema econômico são chamadas de políticas públicas. | P25: Tema 1: Princípios de Economia, Tópico 4: Agentes econômicos. Pág. 14-15. | Q25: 14-15
A26: ECO_T1_025 | B26: Economia | C26: Tema 1 | D26: Cadeias produtivas do agronegócio brasileiro | E26: Médio | F26: Uma cadeia produtiva pode ser definida como: | G26: Uma atividade industrial isolada. | H26: Um conjunto de operações conectadas técnica, comercial e financeiramente. | I26: Um sistema bancário rural. | J26: Um processo exclusivo da indústria. | K26: Uma política pública agrícola. | L26: B | M26: =_xlfn.XLOOKUP(questoes!$L26,Tabela2[LETRA],Tabela2[IND],"",0) -> 1 | N26: 1 | O26: As cadeias produtivas envolvem operações ligadas por relações técnicas, comerciais e financeiras. No agronegócio, o bom relacionamento entre os agentes econômicos melhora a qualidade dos produtos e reduz desperdícios. | P26: Tema 1: Princípios de Economia, Tópico 5: Cadeias produtivas do agronegócio brasileiro. Pág. 15-18. | Q26: 15-18
A27: ECO_T1_026 | B27: Economia | C27: Tema 1 | D27: Cadeias produtivas do agronegócio brasileiro | E27: Difícil | F27: O estudo das cadeias produtivas do agronegócio permite analisar: | G27: Somente exportações. | H27: Apenas a produção agrícola. | I27: Estratégias, contratos e logística entre agentes econômicos. | J27: Somente preços internacionais. | K27: Exclusivamente impostos rurais. | L27: C | M27: =_xlfn.XLOOKUP(questoes!$L27,Tabela2[LETRA],Tabela2[IND],"",0) -> 2 | N27: 2 | O27: O estudo das cadeias produtivas permite analisar estratégias, contratos, logística e problemas estruturais do agronegócio. No agronegócio, o bom relacionamento entre os agentes econômicos melhora a qualidade dos produtos e reduz desperdícios. | P27: Tema 1: Princípios de Economia, Tópico 5: Cadeias produtivas do agronegócio brasileiro. Pág. 15-18. | Q27: 15-18
... A47: ECO_T1_046 | B47: Economia | C47: Tema 1 | D47: Introdução à Economia | E47: Médio | F47: Segundo a apostila, o Plano Agrícola e Pecuário (PAP) possui como objetivo principal: | G47: Regular apenas exportações. | H47: Definir propostas prioritárias para o agronegócio. | I47: Controlar preços industriais. | J47: Criar impostos municipais. | K47: Fiscalizar supermercados. | L47: B | M47: =_xlfn.XLOOKUP(questoes!$L47,Tabela2[LETRA],Tabela2[IND],"",0) -> 1 | N47: 1 | O47: O PAP estabelece propostas prioritárias para o agronegócio como setor da Economia. | P47: Tema 1: Introdução ao agronegócio. Pág. 10-11. | Q47: 10-11
A48: ECO_T2_001 | B48: Economia | C48: Tema 2 | D48: Estruturas de mercado | E48: Ouro | F48: Uma cooperativa de produtores de hortaliças atua em um mercado com centenas de vendedores e compradores. Os produtos comercializados possuem características semelhantes e nenhum produtor consegue influenciar individualmente os preços praticados. Essa situação caracteriza qual estrutura de mercado? | G48: Monopólio. | H48: Monopsônio. | I48: Oligopólio. | J48: Concorrência perfeita. | K48: Concorrência monopolística. | L48: D | M48: =_xlfn.XLOOKUP(questoes!$L48,Tabela2[LETRA],Tabela2[IND],"",0) -> 3 | N48: 3 | O48: A concorrência perfeita caracteriza-se pela existência de um elevado número de compradores e vendedores, de modo que nenhum agente possui poder para influenciar os preços de mercado. Além disso, os produtos comercializados são homogêneos e funcionam como substitutos perfeitos. O preço é definido pela interação entre oferta e demanda. Os mercados agropecuários frequentemente apresentam características próximas a essa estrutura. | P48: Tema 2: Estudo dos Mercados, Tópico 2: Estruturas de mercado, Item: Concorrência perfeita, Pág. 28. | Q48: 28
A49: ECO_T2_002 | B49: Economia | C49: Tema 2 | D49: Estruturas de mercado | E49: Ouro | F49: Em determinada região, uma grande agroindústria é a única compradora da produção de leite de diversos pecuaristas locais. Mesmo havendo vários produtores, o preço pago pelo produto é definido exclusivamente pela empresa compradora. Essa situação representa qual estrutura de mercado? | G49: Monopólio. | H49: Oligopólio. | I49: Concorrência perfeita. | J49: Concorrência monopolística. | K49: Monopsônio. | L49: E | M49: =_xlfn.XLOOKUP(questoes!$L49,Tabela2[LETRA],Tabela2[IND],"",0) -> 4 | N49: 4 | O49: O monopsônio é a estrutura de mercado em que existe apenas um comprador para diversos vendedores. Nessa situação, o preço do produto ou serviço não é determinado pelos produtores, mas sim pelo único comprador. Esse cenário pode ocorrer quando uma grande empresa se torna a principal ou única demandante de determinado produto ou serviço em uma região, influenciando diretamente as condições de negociação. | P49: Tema 2: Estudo dos Mercados, Tópico 2: Estruturas de mercado, Item: Monopsônio, Pág. 30. | Q49: 30
A50: ECO_T2_003 | B50: Economia | C50: Tema 2 | D50: Estruturas de mercado | E50: Ouro | F50: Os setores automobilístico e de telefonia celular no Brasil apresentam poucas empresas dominando grande parte das vendas. As decisões de preço e produção adotadas por uma empresa afetam diretamente o desempenho das demais concorrentes. Essa estrutura de mercado é denominada: | G50: Monopsônio. | H50: Monopólio. | I50: Concorrência perfeita. | J50: Oligopólio. | K50: Concorrência monopolística. | L50: D | M50: =_xlfn.XLOOKUP(questoes!$L50,Tabela2[LETRA],Tabela2[IND],"",0) -> 3 | N50: 3 | O50: O oligopólio é caracterizado pela presença de poucas empresas que controlam a maior parcela do mercado. Uma de suas principais características é a interdependência entre as firmas, pois as decisões tomadas por uma empresa influenciam o comportamento das demais concorrentes. Além disso, as empresas possuem capacidade de afetar os preços por meio da variação do nível de produção. No Brasil, os setores automobilístico, farmacêutico e de telefonia celular são exemplos de mercados oligopolistas. | P50: Tema 2: Estudo dos Mercados, Tópico 2: Estruturas de mercado, Item: Oligopólio, Pág. 31. | Q50: 31
A51: ECO_T2_004 | B51: Economia | C51: Tema 2 | D51: Estruturas de mercado | E51: Ouro | F51: Qual das alternativas apresenta um exemplo de setor econômico brasileiro que possui características típicas de oligopólio? | G51: Produção de hortaliças. | H51: Serviços de saneamento básico. | I51: Setor de telefonia celular. | J51: Comércio eletrônico de pequenos artesãos. | K51: Feiras livres municipais. | L51: C | M51: =_xlfn.XLOOKUP(questoes!$L51,Tabela2[LETRA],Tabela2[IND],"",0) -> 2 | N51: 2 | O51: Segundo a apostila, o setor de telefonia celular no Brasil é um exemplo de oligopólio, pois poucas empresas concentram a maior parte do mercado. Nessa estrutura, as empresas possuem capacidade de influenciar preços e estratégias comerciais, considerando as ações e reações das concorrentes. | P51: Tema 2: Estudo dos Mercados, Tópico 2: Estruturas de mercado, Item: Oligopólio, Pág. 31. | Q51: 31
A52: ECO_T2_005 | B52: Economia | C52: Tema 2 | D52: Estruturas de mercado | E52: Ouro | F52: Uma das principais características do oligopólio é a interdependência entre as empresas. O que esse conceito significa? | G52: As empresas atuam sem considerar as ações das concorrentes. | H52: As empresas possuem liberdade total para definir preços sem concorrência. | I52: As ações de uma empresa podem afetar o desempenho das demais empresas do mercado. | J52: Existe apenas um comprador para diversos vendedores. | K52: Os produtos são sempre homogêneos e sem diferenciação. | L52: C | M52: =_xlfn.XLOOKUP(questoes!$L52,Tabela2[LETRA],Tabela2[IND],"",0) -> 2 | N52: 2 | O52: Na estrutura de mercado oligopolista, existe interdependência entre as firmas. Isso significa que as decisões de uma empresa, como alterar preços, aumentar a produção ou lançar novos produtos, podem afetar diretamente o desempenho das demais concorrentes. Por esse motivo, as empresas consideram constantemente as possíveis reações dos rivais antes de tomar decisões estratégicas. | P52: Tema 2: Estudo dos Mercados, Tópico 2: Estruturas de mercado, Item: Oligopólio, Pág. 31. | Q52: 31
A53: ECO_T2_006 | B53: Economia | C53: Tema 2 | D53: Estruturas de mercado | E53: Ouro | F53: Em relação à quantidade de empresas atuantes, qual característica define corretamente um mercado oligopolista? | G53: Existe apenas uma empresa vendedora. | H53: Existem muitas empresas sem poder de influenciar preços. | I53: Existe apenas um comprador no mercado. | J53: Existem poucas empresas vendedoras controlando grande parte do mercado. | K53: Existem inúmeras empresas comercializando produtos homogêneos. | L53: D | M53: =_xlfn.XLOOKUP(questoes!$L53,Tabela2[LETRA],Tabela2[IND],"",0) -> 3 | N53: 3 | O53: O oligopólio caracteriza-se pela presença de poucas empresas vendedoras que controlam a maior parcela do mercado. Embora nenhuma delas atue como monopolista, todas possuem capacidade de influenciar o mercado e monitoram constantemente as ações das concorrentes. | P53: Tema 2: Estudo dos Mercados, Tópico 2: Estruturas de mercado, Item: Oligopólio, Pág. 31. | Q53: 31
A54: ECO_T2_007 | B54: Economia | C54: Tema 2 | D54: Estruturas de mercado | E54: Ouro | F54: Em uma cidade, apenas uma empresa é responsável pelo fornecimento de energia elétrica para todos os consumidores locais. Não existem empresas concorrentes e a entrada de novos fornecedores é extremamente difícil devido às barreiras regulatórias e aos elevados investimentos necessários. Essa situação caracteriza qual estrutura de mercado? | G54: Concorrência perfeita. | H54: Oligopólio. | I54: Monopólio. | J54: Monopsônio. | K54: Concorrência monopolística. | L54: C | M54: =_xlfn.XLOOKUP(questoes!$L54,Tabela2[LETRA],Tabela2[IND],"",0) -> 2 | N54: 2 | O54: O monopólio é a estrutura de mercado caracterizada pela presença de apenas uma empresa vendedora, sem concorrentes diretos e com elevadas barreiras à entrada de novas firmas. Nessa situação, a empresa monopolista domina a oferta do mercado e os consumidores ficam sujeitos às condições estabelecidas pelo único fornecedor. Serviços de energia elétrica e saneamento básico são exemplos citados na apostila. | P54: Tema 2: Estudo dos Mercados, Tópico 2: Estruturas de mercado, Item: Monopólio, Pág. 30. | Q54: 30
A55: ECO_T2_008 | B55: Economia | C55: Tema 2 | D55: Estruturas de mercado | E55: Ouro | F55: Qual característica é exclusiva da estrutura de mercado denominada monopólio? | G55: Existência de muitos compradores e vendedores. | H55: Presença de produtos homogêneos e substitutos perfeitos. | I55: Existência de poucas empresas concorrentes. | J55: Presença de um único vendedor sem concorrentes diretos. | K55: Liberdade total para entrada e saída de empresas. | L55: D | M55: =_xlfn.XLOOKUP(questoes!$L55,Tabela2[LETRA],Tabela2[IND],"",0) -> 3 | N55: 3 | O55: A principal característica do monopólio é a unicidade, ou seja, existe apenas uma empresa responsável pela oferta do produto ou serviço no mercado. Além disso, há barreiras à entrada de novos concorrentes e o produto não possui substitutos próximos, permitindo que a empresa monopolista exerça grande influência sobre o mercado. | P55: Tema 2: Estudo dos Mercados, Tópico 2: Estruturas de mercado, Item: Monopólio, Pág. 30. | Q55: 30
A56: ECO_T2_009 | B56: Economia | C56: Tema 2 | D56: Estruturas de mercado | E56: Ouro | F56: Em um centro comercial, diversas empresas vendem sabonetes com fragrâncias, embalagens e marcas diferentes. Apesar das diferenças, os consumidores podem substituir um produto por outro conforme suas preferências. Essa situação representa qual estrutura de mercado? | G56: Monopólio. | H56: Monopsônio. | I56: Concorrência perfeita. | J56: Oligopólio. | K56: Concorrência monopolística. | L56: E | M56: =_xlfn.XLOOKUP(questoes!$L56,Tabela2[LETRA],Tabela2[IND],"",0) -> 4 | N56: 4 | O56: A concorrência monopolística caracteriza-se pela existência de muitas empresas atuando no mercado e pela diferenciação dos produtos. Cada empresa oferece um produto com características próprias, como marca, embalagem ou qualidade, mas os consumidores podem substituí-los por produtos semelhantes oferecidos pelos concorrentes. Os setores de sabonetes e cigarros são exemplos citados na apostila. | P56: Tema 2: Estudo dos Mercados, Tópico 2: Estruturas de mercado, Item: Concorrência monopolística, Pág. 32. | Q56: 32
A57: ECO_T2_010 | B57: Economia | C57: Tema 2 | D57: Estruturas de mercado | E57: Ouro | F57: Na concorrência monopolística, qual característica diferencia essa estrutura da concorrência perfeita? | G57: Existe apenas uma empresa atuando no mercado. | H57: Os produtos comercializados são diferenciados entre si. | I57: Não há liberdade para entrada de novas empresas. | J57: Existe apenas um comprador no mercado. | K57: As empresas não competem entre si. | L57: B | M57: =_xlfn.XLOOKUP(questoes!$L57,Tabela2[LETRA],Tabela2[IND],"",0) -> 1 | N57: 1 | O57: A concorrência monopolística é semelhante à concorrência perfeita por apresentar muitas empresas e liberdade de entrada no mercado. No entanto, diferencia-se porque os produtos e serviços comercializados possuem características próprias, como marca, design ou qualidade, permitindo que cada empresa se destaque dos concorrentes. Apesar disso, esses produtos continuam sendo substituíveis entre si. | P57: Tema 2: Estudo dos Mercados, Tópico 2: Estruturas de mercado, Item: Concorrência monopolística, Pág. 32. | Q57: 32
A58: ECO_T2_011 | C58: Tema 2 | D58: Conceituação de mercado | E58: Ouro | F58: Segundo a Economia, o termo mercado pode ser definido como: | G58: O local físico onde ocorrem apenas vendas de produtos agrícolas. | H58: O conjunto de empresas responsáveis pela produção de bens e serviços. | I58: O local ou as condições em que compradores e vendedores entram em contato para realizar trocas de bens e serviços. | J58: O ambiente virtual utilizado exclusivamente para o comércio eletrônico. | K58: O sistema utilizado pelo governo para controlar preços. | L58: C | M58: =_xlfn.XLOOKUP(questoes!$L58,Tabela2[LETRA],Tabela2[IND],"",0) -> 2 | N58: 2 | O58: Na Economia, mercado é definido como o local ou o conjunto de condições em que compradores dispostos a trocar dinheiro por bens e serviços entram em contato com os vendedores desses mesmos bens e serviços. Esse conceito não se restringe a espaços físicos, podendo incluir ambientes digitais e diferentes formas de negociação. | P58: Tema 2: Estudo dos Mercados, Tópico 1: Conceituação de mercado, Item: Conceito de mercado, Pág. 26. | Q58: 26
A59: ECO_T2_012 | C59: Tema 2 | D59: Conceituação de mercado | E59: Ouro | F59: Quando se afirma que um mercado está em expansão, isso significa que: | G59: Há redução na produção e comercialização de bens e serviços. | H59: Está ocorrendo aumento na produção e na comercialização de bens e serviços. | I59: Os consumidores estão reduzindo seus gastos. | J59: O número de empresas no mercado está diminuindo. | K59: Os preços estão sendo controlados pelo governo. | L59: B | M59: =_xlfn.XLOOKUP(questoes!$L59,Tabela2[LETRA],Tabela2[IND],"",0) -> 1 | N59: 1 | O59: Um mercado em expansão é caracterizado pelo aumento da produção e da comercialização de bens e serviços na economia. Esse cenário geralmente está associado ao crescimento da atividade econômica e à ampliação das oportunidades de negócios. | P59: Tema 2: Estudo dos Mercados, Tópico 1: Conceituação de mercado, Item: Mercado em expansão, Pág. 26. | Q59: 26
A60: ECO_T2_013 | C60: Tema 2 | D60: Conceituação de mercado | E60: Ouro | F60: Uma redução contínua na produção e na comercialização de bens e serviços caracteriza qual situação de mercado? | G60: Mercado em equilíbrio. | H60: Mercado em expansão. | I60: Mercado competitivo. | J60: Mercado em contração. | K60: Mercado monopolista. | L60: D | M60: =_xlfn.XLOOKUP(questoes!$L60,Tabela2[LETRA],Tabela2[IND],"",0) -> 3 | N60: 3 | O60: Quando ocorre diminuição na produção e na comercialização de bens e serviços, diz-se que o mercado está em contração. Esse cenário pode indicar desaceleração econômica e redução da atividade produtiva. | P60: Tema 2: Estudo dos Mercados, Tópico 1: Conceituação de mercado, Item: Mercado em contração, Pág. 26. | Q60: 26
A61: ECO_T2_014 | C61: Tema 2 | D61: Conceituação de mercado | E61: Ouro | F61: Qual alternativa apresenta corretamente a diferença entre mercado em expansão e mercado em contração? | G61: No mercado em expansão, os preços diminuem; no mercado em contração, os preços aumentam. | H61: O mercado em expansão possui mais empresas, enquanto o mercado em contração possui menos consumidores. | I61: O mercado em expansão apresenta aumento da produção e comercialização, enquanto o mercado em contração apresenta redução dessas atividades. | J61: O mercado em expansão ocorre apenas no comércio eletrônico, enquanto o mercado em contração ocorre no comércio tradicional. | K61: O mercado em expansão é controlado pelo governo, enquanto o mercado em contração é controlado pelas empresas. | L61: C | M61: =_xlfn.XLOOKUP(questoes!$L61,Tabela2[LETRA],Tabela2[IND],"",0) -> 2 | N61: 2 | O61: O mercado em expansão é caracterizado pelo aumento da produção e da comercialização de bens e serviços. Já o mercado em contração ocorre quando há redução dessas atividades econômicas. Esses conceitos ajudam a compreender o comportamento da economia em diferentes momentos. | P61: Tema 2: Estudo dos Mercados, Tópico 1: Conceituação de mercado, Item: Mercado em expansão e mercado em contração, Pág. 26. | Q61: 26
A62: ECO_T2_015 | C62: Tema 2 | D62: Conceituação de mercado | E62: Ouro | F62: O comércio eletrônico, também conhecido como e-commerce, é caracterizado por: | G62: Transações realizadas exclusivamente em lojas físicas. | H62: Vendas realizadas apenas entre empresas. | I62: Negociações comerciais realizadas por meio de equipamentos eletrônicos, como computadores e smartphones. | J62: Compras realizadas apenas por órgãos governamentais. | K62: Sistemas de troca sem utilização de dinheiro. | L62: C | M62: =_xlfn.XLOOKUP(questoes!$L62,Tabela2[LETRA],Tabela2[IND],"",0) -> 2 | N62: 2 | O62: O e-commerce corresponde às transações comerciais realizadas de forma não presencial por meio de equipamentos eletrônicos, como computadores, tablets e smartphones. Essa modalidade amplia as possibilidades de interação entre compradores e vendedores, criando novas formas de mercado. | P62: Tema 2: Estudo dos Mercados, Tópico 1: Conceituação de mercado, Item: E-commerce, Pág. 26. | Q62: 26
A63: ECO_T2_016 | C63: Tema 2 | D63: Estruturas de mercado | E63: Ouro | F63: Qual característica da concorrência perfeita é definida pela inexistência de barreiras para a entrada ou saída de empresas no mercado? | G63: Atomização. | H63: Homogeneidade. | I63: Mobilidade. | J63: Permeabilidade. | K63: Transparência. | L63: D | M63: =_xlfn.XLOOKUP(questoes!$L63,Tabela2[LETRA],Tabela2[IND],"",0) -> 3 | N63: 3 | O63: A permeabilidade é a característica da concorrência perfeita que representa a inexistência de barreiras técnicas, financeiras ou legais para a entrada e a saída de empresas no mercado. Isso permite que novos agentes econômicos ingressem ou deixem o setor com facilidade, aumentando a competitividade. | P63: Tema 2: Estudo dos Mercados, Tópico 2: Estruturas de mercado, Item: Concorrência perfeita, Pág. 28. | Q63: 28
A64: ECO_T2_017 | C64: Tema 2 | D64: Estruturas de mercado | E64: Ouro | F64: Na estrutura de concorrência perfeita, a característica denominada atomização significa que: | G64: Os produtos são diferenciados entre as empresas. | H64: Existe apenas um vendedor no mercado. | I64: O número de compradores e vendedores é grande o suficiente para que nenhum deles influencie o preço de mercado. | J64: As empresas possuem livre acesso às informações do mercado. | K64: Não existem barreiras para a entrada de novas empresas. | L64: C | M64: =_xlfn.XLOOKUP(questoes!$L64,Tabela2[LETRA],Tabela2[IND],"",0) -> 2 | N64: 2 | O64: A atomização ocorre quando há um grande número de compradores e vendedores no mercado, impedindo que qualquer agente econômico exerça influência significativa sobre o preço. Dessa forma, o preço é determinado pela interação entre oferta e demanda. | P64: Tema 2: Estudo dos Mercados, Tópico 2: Estruturas de mercado, Item: Concorrência perfeita, Pág. 28. | Q64: 28
A65: ECO_T2_018 | C65: Tema 2 | D65: Estruturas de mercado | E65: Ouro | F65: Em uma estrutura de concorrência perfeita, a homogeneidade dos produtos significa que: | G65: Os consumidores possuem informações limitadas sobre os preços. | H65: Os produtos comercializados apresentam características exclusivas. | I65: As empresas estabelecem acordos para definir preços. | J65: Os bens e serviços são semelhantes e podem ser substituídos entre si sem diferenças percebidas pelos consumidores. | K65: Existe apenas uma empresa ofertando o produto. | L65: D | M65: =_xlfn.XLOOKUP(questoes!$L65,Tabela2[LETRA],Tabela2[IND],"",0) -> 3 | N65: 3 | O65: A homogeneidade é uma característica da concorrência perfeita em que os produtos e serviços comercializados são considerados substitutos perfeitos. Isso significa que os consumidores não percebem diferenças relevantes entre os produtos oferecidos pelas diversas empresas. | P65: Tema 2: Estudo dos Mercados, Tópico 2: Estruturas de mercado, Item: Concorrência perfeita, Pág. 28. | Q65: 28
A66: ECO_T2_019 | C66: Tema 2 | D66: Estruturas de mercado | E66: Ouro | F66: Qual característica da concorrência perfeita garante que compradores e vendedores tenham amplo acesso às informações sobre preços e métodos de produção? | G66: Mobilidade. | H66: Transparência. | I66: Unicidade. | J66: Permeabilidade. | K66: Interdependência. | L66: B | M66: =_xlfn.XLOOKUP(questoes!$L66,Tabela2[LETRA],Tabela2[IND],"",0) -> 1 | N66: 1 | O66: A transparência é a característica da concorrência perfeita que assegura amplo acesso às informações sobre preços, custos e métodos de produção. Esse fluxo de informações contribui para a tomada de decisão dos agentes econômicos e favorece a eficiência do mercado. | P66: Tema 2: Estudo dos Mercados, Tópico 2: Estruturas de mercado, Item: Concorrência perfeita, Pág. 28. | Q66: 28
A67: ECO_T2_020 | C67: Tema 2 | D67: Estruturas de mercado | E67: Ouro | F67: Qual das alternativas apresenta uma característica típica do monopólio? | G67: Existência de muitas empresas concorrentes. | H67: Livre entrada de novos concorrentes no mercado. | I67: Presença de um único vendedor e existência de barreiras à entrada de novas empresas. | J67: Produtos homogêneos e ausência de poder de mercado. | K67: Grande número de compradores e vendedores sem influência sobre os preços. | L67: C | M67: =_xlfn.XLOOKUP(questoes!$L67,Tabela2[LETRA],Tabela2[IND],"",0) -> 2 | N67: 2 | O67: O monopólio caracteriza-se pela presença de uma única empresa ofertante, ausência de concorrentes diretos e existência de barreiras que dificultam a entrada de novas firmas. Nessa estrutura, a empresa monopolista possui elevado poder para influenciar preços e condições de mercado. | P67: Tema 2: Estudo dos Mercados, Tópico 2: Estruturas de mercado, Item: Monopólio, Pág. 30. | Q67: 30
A68: ECO_T3_001 | B68: Economia | C68: Tema 3 | D68: Análise Mercadológica de Oferta e de Demanda | E68: Ouro | F68: Uma estiagem prolongada reduziu significativamente a produção de milho em determinada região, enquanto o consumo do produto permaneceu inalterado. Qual situação de mercado tende a ocorrer nesse cenário? | G68: Excesso de oferta. | H68: Equilíbrio de mercado. | I68: Excesso de demanda. | J68: Redução da procura. | K68: Aumento da oferta. | L68: C | M68: =_xlfn.XLOOKUP(questoes!$L68,Tabela2[LETRA],Tabela2[IND],"",0) -> 2 | N68: 2 | O68: Quando ocorre uma redução da oferta de um produto e a demanda permanece constante, estabelece-se uma situação de excesso de demanda, também denominada escassez de oferta. Nessa situação, os consumidores desejam adquirir uma quantidade maior do que a disponível no mercado, o que tende a elevar os preços até que um novo equilíbrio seja alcançado. | P68: Tema 3: Teoria do Consumidor, Tópico 1: Análise Mercadológica de Oferta e de Demanda, Item: Excesso e escassez de mercado, Pág. 47. | Q68: 47
A69: ECO_T3_002 | B69: Economia | C69: Tema 3 | D69: Análise Mercadológica de Oferta e de Demanda | E69: Ouro | F69: Em um mercado de hortaliças, a quantidade ofertada é superior à quantidade demandada em razão de uma safra excepcionalmente produtiva. Como essa situação é classificada? | G69: Excesso de demanda. | H69: Escassez de oferta. | I69: Equilíbrio de mercado. | J69: Excesso de oferta. | K69: Aumento da renda dos consumidores. | L69: D | M69: =_xlfn.XLOOKUP(questoes!$L69,Tabela2[LETRA],Tabela2[IND],"",0) -> 3 | N69: 3 | O69: O excesso de oferta ocorre quando a quantidade ofertada de um bem é maior que a quantidade demandada. Nessa situação, há sobra de produtos no mercado e os vendedores tendem a reduzir os preços para estimular as vendas e restabelecer o equilíbrio entre oferta e demanda. | P69: Tema 3: Teoria do Consumidor, Tópico 1: Análise Mercadológica de Oferta e de Demanda, Item: Excesso e escassez de mercado, Pág. 47. | Q69: 47
A70: ECO_T3_003 | B70: Economia | C70: Tema 3 | D70: Análise Mercadológica de Oferta e de Demanda | E70: Ouro | F70: O equilíbrio de mercado é alcançado quando: | G70: A quantidade ofertada é maior que a quantidade demandada. | H70: Os consumidores deixam de adquirir o produto. | I70: A quantidade demandada é igual à quantidade ofertada. | J70: Os preços são definidos exclusivamente pelos vendedores. | K70: Os custos de produção são reduzidos. | L70: C | M70: =_xlfn.XLOOKUP(questoes!$L70,Tabela2[LETRA],Tabela2[IND],"",0) -> 2 | N70: 2 | O70: O equilíbrio de mercado ocorre no ponto de interseção entre as curvas de oferta e demanda. Nessa situação, a quantidade que os consumidores desejam comprar é exatamente igual à quantidade que os vendedores desejam oferecer, estabelecendo o chamado preço de equilíbrio. | P70: Tema 3: Teoria do Consumidor, Tópico 1: Análise Mercadológica de Oferta e de Demanda, Item: Equilíbrio de mercado, Pág. 45. | Q70: 45
A71: ECO_T3_004 | B71: Economia | C71: Tema 3 | D71: Análise Mercadológica de Oferta e de Demanda | E71: Ouro | F71: Após fortes chuvas, a produção de tomate foi reduzida e a quantidade disponível no mercado tornou-se insuficiente para atender à procura dos consumidores. Qual tendência é esperada para o preço desse produto? | G71: O preço tende a diminuir até zerar. | H71: O preço tende a permanecer inalterado. | I71: O preço tende a aumentar até atingir um novo equilíbrio. | J71: O preço será determinado apenas pelos consumidores. | K71: O preço deixará de ser influenciado pela oferta. | L71: C | M71: =_xlfn.XLOOKUP(questoes!$L71,Tabela2[LETRA],Tabela2[IND],"",0) -> 2 | N71: 2 | O71: Quando ocorre escassez de oferta, os consumidores passam a disputar uma quantidade menor de produtos disponíveis no mercado. Essa situação provoca aumento dos preços até que seja alcançado um novo ponto de equilíbrio entre a quantidade ofertada e a quantidade demandada. | P71: Tema 3: Teoria do Consumidor, Tópico 1: Análise Mercadológica de Oferta e de Demanda, Item: Excesso e escassez de mercado, Pág. 47. | Q71: 47
A72: ECO_T3_005 | B72: Economia | C72: Tema 3 | D72: Análise Mercadológica de Oferta e de Demanda | E72: Ouro | F72: Uma empresa do setor agroindustrial adotou máquinas mais modernas, aumentando sua produtividade sem alterar os preços de venda dos produtos. De acordo com a Teoria do Consumidor, essa mudança tende a provocar qual efeito sobre a curva de oferta? | G72: Movimento ao longo da curva de demanda. | H72: Deslocamento da curva de oferta para a direita. | I72: Deslocamento da curva de demanda para a esquerda. | J72: Redução da quantidade demandada. | K72: Manutenção da oferta no mesmo nível. | L72: B | M72: =_xlfn.XLOOKUP(questoes!$L72,Tabela2[LETRA],Tabela2[IND],"",0) -> 1 | N72: 1 | O72: O deslocamento da curva de oferta ocorre quando variáveis que influenciam a decisão dos produtores são alteradas, mantendo-se os preços constantes. A adoção de novas tecnologias aumenta a eficiência produtiva e permite que as empresas ofertem maiores quantidades aos mesmos preços, deslocando a curva de oferta para a direita. | P72: Tema 3: Teoria do Consumidor, Tópico 1: Análise Mercadológica de Oferta e de Demanda, Item: Deslocamento da curva de oferta, Pág. 44. | Q72: 44
A73: ECO_T3_006 | B73: Economia | C73: Tema 3 | D73: Análise Mercadológica de Oferta e de Demanda | E73: Ouro | F73: Qual das alternativas apresenta apenas fatores que podem provocar o deslocamento da curva de oferta de um produto? | G73: Preço do produto e renda do consumidor. | H73: Tecnologia e preferências do consumidor. | I73: Condições climáticas e preço do produto. | J73: Tecnologia, condições climáticas e impostos governamentais. | K73: Preço de produtos substitutos e renda do consumidor. | L73: D | M73: =_xlfn.XLOOKUP(questoes!$L73,Tabela2[LETRA],Tabela2[IND],"",0) -> 3 | N73: 3 | O73: O deslocamento da curva de oferta ocorre quando variáveis que afetam a expectativa dos produtores são modificadas, mantendo-se os preços constantes. Entre essas variáveis estão a tecnologia, as condições climáticas, o suprimento de insumos e os impostos ou subsídios governamentais. Mudanças no preço do próprio produto geram apenas movimentos ao longo da curva de oferta. | P73: Tema 3: Teoria do Consumidor, Tópico 1: Análise Mercadológica de Oferta e de Demanda, Item: Deslocamento da curva de oferta, Pág. 44. | Q73: 44
A74: ECO_T3_007 | B74: Economia | C74: Tema 3 | D74: Análise Mercadológica de Oferta e de Demanda | E74: Ouro | F74: Uma seca prolongada reduziu a produtividade das lavouras de café em determinada região, mesmo sem alteração no preço do produto. Qual será o efeito mais provável sobre a curva de oferta? | G74: Deslocamento da curva de oferta para a esquerda. | H74: Movimento ao longo da curva de oferta. | I74: Deslocamento da curva de demanda para a direita. | J74: Aumento da quantidade demandada. | K74: Deslocamento da curva de demanda para a esquerda. | L74: A | M74: =_xlfn.XLOOKUP(questoes!$L74,Tabela2[LETRA],Tabela2[IND],"",0) -> 0 | N74: 0 | O74: As condições climáticas são uma das variáveis que influenciam a oferta de bens e serviços. Eventos climáticos adversos, como secas prolongadas, reduzem a capacidade produtiva e fazem com que os produtores ofertem menores quantidades aos mesmos preços, provocando o deslocamento da curva de oferta para a esquerda. | P74: Tema 3: Teoria do Consumidor, Tópico 1: Análise Mercadológica de Oferta e de Demanda, Item: Deslocamento da curva de oferta, Pág. 44. | Q74: 44
A75: ECO_T3_008 | B75: Economia | C75: Tema 3 | D75: Análise Mercadológica de Oferta e de Demanda | E75: Ouro | F75: Qual situação representa uma alteração que provoca apenas movimento ao longo da curva de oferta, sem deslocá-la? | G75: Aumento dos impostos sobre a produção. | H75: Melhoria das condições climáticas. | I75: Redução no custo dos insumos agrícolas. | J75: Variação no preço do próprio produto. | K75: Concessão de subsídios governamentais. | L75: D | M75: =_xlfn.XLOOKUP(questoes!$L75,Tabela2[LETRA],Tabela2[IND],"",0) -> 3 | N75: 3 | O75: Segundo a Lei da Oferta, quando ocorre variação no preço do próprio produto, há alteração apenas na quantidade ofertada, gerando movimento ao longo da curva de oferta. O deslocamento da curva ocorre somente quando variáveis como tecnologia, clima, custos de produção, impostos ou subsídios são modificadas, mantendo-se os preços constantes. | P75: Tema 3: Teoria do Consumidor, Tópico 1: Análise Mercadológica de Oferta e de Demanda, Item: Lei da Oferta, Pág. 42. | Q75: 42
A76: ECO_T3_009 | B76: Economia | C76: Tema 3 | D76: Análise Mercadológica de Oferta e de Demanda | E76: Ouro | F76: Segundo a Lei da Demanda, o que ocorre com a quantidade demandada de um produto quando seu preço diminui, mantendo-se constantes as demais variáveis? | G76: A quantidade demandada diminui. | H76: A quantidade demandada aumenta. | I76: A quantidade ofertada aumenta. | J76: A oferta do produto diminui. | K76: A curva de demanda desloca-se para a esquerda. | L76: B | M76: =_xlfn.XLOOKUP(questoes!$L76,Tabela2[LETRA],Tabela2[IND],"",0) -> 1 | N76: 1 | O76: De acordo com a Lei da Demanda, mantendo-se constantes as demais variáveis (ceteris paribus), existe uma relação inversa entre preço e quantidade demandada. Assim, quando o preço de um bem diminui, a quantidade demandada aumenta. Por exemplo, se o preço da saca de milho utilizada na alimentação animal cair, os produtores podem aumentar a quantidade adquirida. | P76: Tema 3: Teoria do Consumidor, Tópico 1: Análise Mercadológica de Oferta e de Demanda, Item: Lei da Demanda, Pág. 38. | Q76: 38
A77: ECO_T3_010 | B77: Economia | C77: Tema 3 | D77: Análise Mercadológica de Oferta e de Demanda | E77: Ouro | F77: Uma redução no preço da saca de milho de R$ 60,00 para R$ 50,00 levou os avicultores a comprar maior quantidade do produto para produção de ração. Esse exemplo representa: | G77: Deslocamento da curva de demanda. | H77: Movimento ao longo da curva de oferta. | I77: Movimento ao longo da curva de demanda. | J77: Deslocamento da curva de oferta. | K77: Equilíbrio de mercado. | L77: C | M77: =_xlfn.XLOOKUP(questoes!$L77,Tabela2[LETRA],Tabela2[IND],"",0) -> 2 | N77: 2 | O77: Quando ocorre alteração no preço do próprio produto, há mudança apenas na quantidade demandada, caracterizando um movimento ao longo da curva de demanda. No exemplo, a redução no preço do milho aumentou a quantidade demandada pelos avicultores, sem alterar a posição da curva de demanda. | P77: Tema 3: Teoria do Consumidor, Tópico 1: Análise Mercadológica de Oferta e de Demanda, Item: Movimento ao longo da curva de demanda, Pág. 40. | Q77: 40
A78: ECO_T3_011 | B78: Economia | C78: Tema 3 | D78: Análise Mercadológica de Oferta e de Demanda | E78: Ouro | F78: Segundo a Lei da Oferta, o que tende a acontecer com a quantidade ofertada de um produto quando seu preço aumenta, mantendo-se constantes as demais variáveis? | G78: A quantidade ofertada diminui. | H78: A quantidade demandada aumenta. | I78: A quantidade ofertada aumenta. | J78: A curva de oferta desloca-se para a esquerda. | K78: O custo de produção diminui automaticamente. | L78: C | M78: =_xlfn.XLOOKUP(questoes!$L78,Tabela2[LETRA],Tabela2[IND],"",0) -> 2 | N78: 2 | O78: De acordo com a Lei da Oferta, mantendo-se constantes as demais variáveis (ceteris paribus), quando o preço de um bem aumenta, a quantidade ofertada pelos produtores também aumenta. Isso ocorre porque preços mais elevados tornam a atividade mais atrativa economicamente. | P78: Tema 3: Teoria do Consumidor, Tópico 1: Análise Mercadológica de Oferta e de Demanda, Item: Lei da Oferta, Pág. 42. | Q78: 42
A79: ECO_T3_012 | B79: Economia | C79: Tema 3 | D79: Análise Mercadológica de Oferta e de Demanda | E79: Ouro | F79: Se o preço pago ao produtor de leite aumentar de R$ 1,50 para R$ 1,80 por litro, levando mais produtores a comercializarem leite com os laticínios, esse comportamento representa: | G79: Deslocamento da curva de oferta. | H79: Movimento ao longo da curva de oferta. | I79: Deslocamento da curva de demanda. | J79: Excesso de demanda. | K79: Redução da quantidade ofertada. | L79: B | M79: =_xlfn.XLOOKUP(questoes!$L79,Tabela2[LETRA],Tabela2[IND],"",0) -> 1 | N79: 1 | O79: Alterações no preço do próprio produto provocam mudanças apenas na quantidade ofertada, gerando movimento ao longo da curva de oferta. No exemplo, o aumento do preço do leite incentiva os produtores a ofertarem maiores quantidades ao mercado. | P79: Tema 3: Teoria do Consumidor, Tópico 1: Análise Mercadológica de Oferta e de Demanda, Item: Movimento ao longo da curva de oferta, Pág. 44. | Q79: 44
... A108: ECO_T5_003 | B108: Economia | C108: Tema 5 | D108: Análise da Teoria da Empresa Rural | E108: Ouro | F108: Segundo a Teoria da Firma, qual é o principal objetivo econômico de uma empresa rural? | G108: Ampliar a quantidade de funcionários. | H108: Maximizar o lucro. | I108: Produzir a maior quantidade possível. | J108: Reduzir os custos fixos a zero. | K108: Aumentar continuamente a área cultivada. | L108: B | M108: =_xlfn.XLOOKUP(questoes!$L108,Tabela2[LETRA],Tabela2[IND],"",0) -> 1 | N108: 1 | O108: O objetivo central de toda empresa é a maximização do lucro. Na empresa rural, isso significa utilizar os recursos produtivos disponíveis, como terra, trabalho e capital, da forma mais eficiente possível para obter a maior diferença positiva entre a receita total e os custos totais de produção. | P108: Tema 5: Teoria da Firma, Tópico 1: Análise da Teoria da Empresa Rural, Item: Receita, custo e lucro, Pág. 62. | Q108: 62
A109: ECO_T5_004 | C109: Tema 5 | D109: Análise da Teoria da Empresa Rural | E109: Ouro | F109: De acordo com a Teoria da Firma, qual condição deve ser atendida para que uma empresa rural alcance o lucro máximo? | G109: A receita total deve ser igual ao custo total. | H109: O custo marginal deve ser maior que a receita marginal. | I109: A receita marginal deve ser igual ao custo marginal. | J109: O custo fixo deve ser igual ao custo variável. | K109: A produção deve atingir sua capacidade máxima. | L109: C | M109: =_xlfn.XLOOKUP(questoes!$L109,Tabela2[LETRA],Tabela2[IND],"",0) -> 2 | N109: 2 | O109: Segundo a Teoria da Firma, o lucro máximo é alcançado no ponto em que a receita marginal (RMg) é igual ao custo marginal (CMg). Isso significa que a receita gerada pela venda de uma unidade adicional é exatamente igual ao custo necessário para produzi-la. Produzir além desse ponto reduz a rentabilidade da atividade. | P109: Tema 5: Teoria da Firma, Tópico 1: Análise da Teoria da Empresa Rural, Item: Lucro máximo, Pág. 73. | Q109: 73
A110: ECO_T5_005 | B110: Economia | C110: Tema 5 | D110: Análise da Teoria da Empresa Rural | E110: Ouro | F110: O que representa o custo marginal na análise econômica da empresa rural? | G110: O custo total da produção em determinado período. | H110: O valor gasto com os custos fixos da propriedade. | I110: O acréscimo no custo total decorrente da produção de uma unidade adicional. | J110: A diferença entre receita total e custo total. | K110: O custo médio de todas as unidades produzidas. | L110: C | M110: =_xlfn.XLOOKUP(questoes!$L110,Tabela2[LETRA],Tabela2[IND],"",0) -> 2 | N110: 2 | O110: O custo marginal corresponde ao acréscimo no custo total gerado pela produção de uma unidade adicional do bem ou serviço. Esse indicador é fundamental para a tomada de decisão do produtor rural, pois auxilia na definição do nível ótimo de produção. | P110: Tema 5: Teoria da Firma, Tópico 1: Análise da Teoria da Empresa Rural, Item: Custos médio e marginal, Pág. 68. | Q110: 68
A111: ECO_T5_006 | B111: Economia | C111: Tema 5 | D111: Análise da Teoria da Empresa Rural | E111: Ouro | F111: A receita marginal pode ser definida como: | G111: A receita obtida com a venda total da produção. | H111: A diferença entre a receita total e os custos variáveis. | I111: A variação da receita total decorrente da venda de uma unidade adicional do produto. | J111: O valor médio recebido por unidade comercializada. | K111: A soma das receitas obtidas em diferentes períodos. | L111: C | M111: =_xlfn.XLOOKUP(questoes!$L111,Tabela2[LETRA],Tabela2[IND],"",0) -> 2 | N111: 2 | O111: A receita marginal representa a variação da receita total obtida pela empresa quando uma unidade adicional do produto é vendida. Esse conceito é utilizado juntamente com o custo marginal para determinar o ponto de maximização do lucro. | P111: Tema 5: Teoria da Firma, Tópico 1: Análise da Teoria da Empresa Rural, Item: Receita marginal, Pág. 72. | Q111: 72
A112: ECO_T5_007 | B112: Economia | C112: Tema 5 | D112: Análise da Teoria da Empresa Rural | E112: Ouro | F112: Um produtor rural verificou que o custo marginal para produzir uma caixa adicional de morangos é de R$ 45,00, enquanto a receita marginal obtida com a venda dessa caixa é de R$ 60,00. Considerando a Teoria da Firma, qual decisão tende a aumentar o lucro da propriedade? | G112: Reduzir a produção imediatamente. | H112: Manter o nível atual de produção. | I112: Aumentar a produção até que o custo marginal se iguale à receita marginal. | J112: Interromper a comercialização do produto. | K112: Reduzir o preço de venda independentemente dos custos. | L112: C | M112: =_xlfn.XLOOKUP(questoes!$L112,Tabela2[LETRA],Tabela2[IND],"",0) -> 2 | N112: 2 | O112: Quando a receita marginal é maior que o custo marginal, a venda de uma unidade adicional gera aumento no lucro da empresa. Portanto, o produtor deve ampliar a produção até o ponto em que a receita marginal se iguale ao custo marginal, condição necessária para a maximização do lucro. | P112: Tema 5: Teoria da Firma, Tópico 1: Análise da Teoria da Empresa Rural, Item: Lucro máximo, Pág. 73. | Q112: 73
A113: ECO_T5_008 | B113: Economia | C113: Tema 5 | D113: Análise da Teoria da Empresa Rural | E113: Ouro | F113: Qual alternativa apresenta corretamente as variáveis utilizadas pela Teoria da Firma para identificar o ponto de lucro máximo? | G113: Custo fixo e custo variável. | H113: Receita total e custo total. | I113: Custo médio e receita média. | J113: Custo marginal e receita marginal. | K113: Receita líquida e custo operacional. | L113: D | M113: =_xlfn.XLOOKUP(questoes!$L113,Tabela2[LETRA],Tabela2[IND],"",0) -> 3 | N113: 3 | O113: A Teoria da Firma utiliza as variáveis custo marginal e receita marginal para identificar o ponto de lucro máximo. O custo marginal representa o acréscimo de custo gerado pela produção de uma unidade adicional, enquanto a receita marginal corresponde ao aumento da receita decorrente da venda dessa unidade adicional. | P113: Tema 5: Teoria da Firma, Tópico 1: Análise da Teoria da Empresa Rural, Item: Lucro máximo, Pág. 73. | Q113: 73
A114: ECO_T5_009 | B114: Economia | C114: Tema 5 | D114: Análise da Teoria da Empresa Rural | E114: Ouro | F114: Segundo a Teoria da Firma, em qual situação uma empresa rural obtém lucro? | G114: Quando os custos totais são menores que a receita total. | H114: Quando a receita total é igual aos custos totais. | I114: Quando os custos variáveis são maiores que a receita total. | J114: Quando os custos totais superam a receita total. | K114: Quando os custos fixos são iguais aos custos variáveis. | L114: A | M114: =_xlfn.XLOOKUP(questoes!$L114,Tabela2[LETRA],Tabela2[IND],"",0) -> 0 | N114: 0 | O114: O lucro é obtido quando a receita total supera os custos totais da atividade. A relação pode ser expressa pela fórmula Lucro = Receita Total − Custos Totais. Dessa forma, sempre que os custos de produção e os gastos operacionais forem inferiores à receita obtida com as vendas, a empresa apresentará resultado positivo. | P114: Tema 5: Teoria da Firma, Tópico 1: Análise da Teoria da Empresa Rural, Item: Receita, custo e lucro, Pág. 63. | Q114: 63
A115: ECO_T5_010 | B115: Economia | C115: Tema 5 | D115: Análise da Teoria da Empresa Rural | E115: Ouro | F115: Uma propriedade rural obteve receita total de R$ 85.000,00 e custos totais de R$ 72.000,00 em determinado período. Qual foi o lucro obtido pela empresa? | G115: R$ 13.000,00. | H115: R$ 72.000,00. | I115: R$ 85.000,00. | J115: R$ 157.000,00. | K115: R$ 7.200,00. | L115: A | M115: =_xlfn.XLOOKUP(questoes!$L115,Tabela2[LETRA],Tabela2[IND],"",0) -> 0 | N115: 0 | O115: O lucro é calculado pela diferença entre a receita total e os custos totais. Nesse caso, o produtor obteve lucro de R$ 13.000,00, resultado da operação R$ 85.000,00 − R$ 72.000,00. Esse indicador permite avaliar a viabilidade econômica da atividade rural. | P115: Tema 5: Teoria da Firma, Tópico 1: Análise da Teoria da Empresa Rural, Item: Receita, custo e lucro, Pág. 63. | Q115: 63
A116: ECO_T5_011 | B116: Economia | C116: Tema 5 | D116: Análise da Teoria da Empresa Rural | E116: Ouro | F116: O aumento da receita de vendas garante, necessariamente, o aumento do lucro de uma empresa rural? | G116: Sim, porque toda elevação da receita aumenta automaticamente o lucro. | H116: Não, porque os custos podem aumentar em proporção igual ou superior à receita. | I116: Sim, desde que a produção seja ampliada. | J116: Não, porque a receita não influencia o lucro. | K116: Sim, desde que os custos fixos permaneçam constantes. | L116: B | M116: =_xlfn.XLOOKUP(questoes!$L116,Tabela2[LETRA],Tabela2[IND],"",0) -> 1 | N116: 1 | O116: O aumento da receita não garante, necessariamente, maior lucro. Para que o lucro aumente, é necessário que o crescimento da receita seja superior ao aumento dos custos totais. Caso as despesas cresçam na mesma proporção ou acima da receita, o lucro poderá permanecer inalterado ou até diminuir. | P116: Tema 5: Teoria da Firma, Tópico 1: Análise da Teoria da Empresa Rural, Item: Receita, custo e lucro, Pág. 63. | Q116: 63
A117: ECO_T5_012 | B117: Economia | C117: Tema 5 | D117: Análise da Teoria da Empresa Rural | E117: Ouro | F117: Produzir uma quantidade maior de bens garante automaticamente maior lucro para a empresa rural? | G117: Sim, porque o aumento da produção sempre reduz os custos totais. | H117: Não, porque o aumento da produção pode elevar os custos acima da receita obtida. | I117: Sim, desde que a empresa venda toda a produção. | J117: Não, porque a quantidade produzida não interfere na receita. | K117: Sim, porque maiores volumes de produção eliminam os custos fixos. | L117: B | M117: =_xlfn.XLOOKUP(questoes!$L117,Tabela2[LETRA],Tabela2[IND],"",0) -> 1 | N117: 1 | O117: O aumento da quantidade produzida não assegura maior lucro. O produtor deve avaliar se a receita adicional obtida com a ampliação da produção é suficiente para cobrir os custos adicionais envolvidos. Produzir além do nível economicamente eficiente pode reduzir a rentabilidade da atividade. | P117: Tema 5: Teoria da Firma, Tópico 1: Análise da Teoria da Empresa Rural, Item: Receita, custo e lucro, Pág. 63. | Q117: 63
A118: ECO_T5_013 | B118: Economia | C118: Tema 5 | D118: Análise da Teoria da Empresa Rural | E118: Ouro | F118: Quando a receita total de uma empresa rural é exatamente igual ao custo total, qual é o resultado econômico obtido? | G118: Lucro máximo. | H118: Prejuízo operacional. | I118: Lucro extraordinário. | J118: Ponto de equilíbrio. | K118: Receita marginal positiva. | L118: D | M118: =_xlfn.XLOOKUP(questoes!$L118,Tabela2[LETRA],Tabela2[IND],"",0) -> 3 | N118: 3 | O118: Quando a receita total é igual ao custo total, a empresa atinge o ponto de equilíbrio. Nessa situação, não há lucro nem prejuízo, pois todos os custos da atividade foram cobertos pelas receitas obtidas com as vendas. | P118: Tema 5: Teoria da Firma, Tópico 1: Análise da Teoria da Empresa Rural, Item: Receita, custo e lucro, Pág. 63. | Q118: 63
A119: ECO_T5_014 | B119: Economia | C119: Tema 5 | D119: Análise da Teoria da Empresa Rural | E119: Ouro | F119: Qual das alternativas apresenta um exemplo de fator de natureza interna que influencia a tomada de decisão do produtor rural? | G119: Políticas governamentais. | H119: Nível de renda da população local. | I119: Tecnologia de produção disponível no mercado. | J119: Necessidades presentes e futuras do negócio. | K119: Condições climáticas da região. | L119: D | M119: =_xlfn.XLOOKUP(questoes!$L119,Tabela2[LETRA],Tabela2[IND],"",0) -> 3 | N119: 3 | O119: Os fatores internos são aqueles relacionados às características e condições próprias da empresa rural e do produtor. Entre eles, destacam-se as necessidades presentes e futuras do negócio, a experiência do produtor, seus conhecimentos técnicos e administrativos e a disponibilidade de recursos produtivos. Esses fatores influenciam diretamente o planejamento e a tomada de decisão na propriedade rural. | P119: Tema 5: Teoria da Firma, Tópico 1: Análise da Teoria da Empresa Rural, Item: Fatores de natureza interna e externa, Pág. 60. | Q119: 60
A120: ECO_T5_015 | B120: Economia | C120: Tema 5 | D120: Análise da Teoria da Empresa Rural | E120: Ouro | F120: Qual das alternativas representa um fator de natureza externa que pode influenciar o desempenho de uma empresa rural? | G120: Habilidade do produtor para realizar as atividades produtivas. | H120: Idade do produtor rural. | I120: Políticas governamentais. | J120: Necessidades futuras do negócio. | K120: Conhecimento técnico e administrativo do produtor. | L120: C | M120: =_xlfn.XLOOKUP(questoes!$L120,Tabela2[LETRA],Tabela2[IND],"",0) -> 2 | N120: 2 | O120: Os fatores externos são aqueles que estão fora do controle direto do produtor rural, mas influenciam o desempenho da propriedade. Entre eles, destacam-se as políticas governamentais, o nível de renda da população, a tecnologia disponível e as condições de mercado. | P120: Tema 5: Teoria da Firma, Tópico 1: Análise da Teoria da Empresa Rural, Item: Fatores de natureza interna e externa, Pág. 60. | Q120: 60
A121: ECO_T5_016 | B121: Economia | C121: Tema 5 | D121: Análise da Teoria da Empresa Rural | E121: Ouro | F121: O conhecimento técnico e administrativo do produtor rural é classificado como: | G121: Fator de natureza externa. | H121: Fator de natureza interna. | I121: Fator macroeconômico. | J121: Fator climático. | K121: Fator institucional. | L121: B | M121: =_xlfn.XLOOKUP(questoes!$L121,Tabela2[LETRA],Tabela2[IND],"",0) -> 1 | N121: 1 | O121: O conhecimento técnico e administrativo do produtor é considerado um fator de natureza interna, pois está relacionado às características individuais e às competências gerenciais do responsável pela empresa rural. Esses fatores influenciam diretamente a eficiência da gestão e os resultados econômicos da propriedade. | P121: Tema 5: Teoria da Firma, Tópico 1: Análise da Teoria da Empresa Rural, Item: Fatores de natureza interna e externa, Pág. 60. | Q121: 60
... A146: ECO_T6_020 | B146: Economia | C146: Tema 6 | D146: Aspectos Iniciais de Desenvolvimento Rural | E146: Ouro | F146: Segundo a dimensão cultural do desenvolvimento sustentável, é necessário: | G146: Uniformizar os hábitos e costumes da população. | H146: Desconsiderar as características regionais. | I146: Valorizar a diversidade cultural e os valores das diferentes sociedades. | J146: Concentrar a produção em grandes centros urbanos. | K146: Substituir práticas tradicionais por tecnologias modernas. | L146: C | M146: =_xlfn.XLOOKUP(questoes!$L146,Tabela2[LETRA],Tabela2[IND],"",0) -> 2 | N146: 2 | O146: A dimensão cultural do desenvolvimento sustentável considera os valores e a diversidade cultural dos povos, conciliando tradições locais e desenvolvimento econômico sustentável. Essa dimensão reconhece a importância das diferentes identidades culturais na construção de sociedades mais equilibradas e inclusivas. | P146: Tema 6: Desenvolvimento Rural no Brasil, Tópico 1: Aspectos Iniciais de Desenvolvimento Rural, Item: Desenvolvimento agrícola sustentável, Pág. 80. | Q146: 80

Sheet Planilha1
A1: LETRA | B1: IND
A2: A | B2: 0
A3: B | B3: 1
A4: C | B4: 2
A5: D | B5: 3
A6: E | B6: 4
